DToolslib/Color_Text.py
DToolslib/Data_Handler.py
DToolslib/Enum_Static.py
DToolslib/JFTimer.py
DToolslib/Signal_Event.py
DToolslib/__init__.py
DToolslib/Inner_Decorators/__init__.py
DToolslib/Inner_Decorators/boundary_check.py
DToolslib/Inner_Decorators/time_counter.py
DToolslib/Inner_Decorators/try_except_log.py
DToolslib/Inner_Decorators/who_called_me.py
DToolslib/_JFLogger/_Compressed_Thread.py
DToolslib/_JFLogger/_JFLogger.py
DToolslib/_JFLogger/_JFLogger_Group.py
DToolslib/_JFLogger/_LogEnum.py
DToolslib/_JFLogger/_Logging_Listener.py
DToolslib/_JFLogger/__init__.py
dtoolslib-2.4.20.dist-info/licenses/LICENSE
dtoolslib-2.4.20.dist-info/METADATA
dtoolslib-2.4.20.dist-info/WHEEL
dtoolslib-2.4.20.dist-info/top_level.txt
dtoolslib-2.4.20.dist-info/RECORD
