Metadata-Version: 2.4
Name: DToolslib
Version: 2.4.20
Summary: A simple and miscellaneous utility library containing multiple utility scripts. 一个简单且杂的工具库, 包含多个工具脚本
Author: Jf-JIN
License: MIT License
Project-URL: Homepage, https://github.com/Jf-JIN/DToolslib
Project-URL: Repository, https://github.com/Jf-JIN/DToolslib
Project-URL: Documentation, https://github.com/Jf-JIN/DToolslib/wiki
Keywords: signal,logger,logging,enum,timer
Classifier: Development Status :: 2 - Pre-Alpha
Classifier: Intended Audience :: Developers
Classifier: License :: OSI Approved :: MIT License
Classifier: Programming Language :: Python :: 3.11
Classifier: Operating System :: OS Independent
Classifier: Topic :: Software Development :: Libraries
Requires-Python: >=3.11
License-File: LICENSE
Requires-Dist: wrapt
Requires-Dist: psutil
Dynamic: license-file
